Analogy/ComparisonPOSNumpy.py
Analogy/NLP_POSPair.py
Analogy/__init__.py
Analogy-0.1.dist-info/LICENSE.txt
Analogy-0.1.dist-info/METADATA
Analogy-0.1.dist-info/WHEEL
Analogy-0.1.dist-info/top_level.txt
Analogy-0.1.dist-info/RECORD
