Metadata-Version: 2.1
Name: Analogy
Version: 0.1
Summary: Experimental Open-source Natural Language Processing project for similiarity and difference retrieval
Home-page: https://github.com/jmacwan/Analogy
Author: Jim Macwan
Author-email: jimmacwan94@gmail.com
License: UNKNOWN
Platform: UNKNOWN
Classifier: Programming Language :: Python :: 3
Classifier: License :: OSI Approved :: GNU General Public License v3 (GPLv3)
Classifier: Operating System :: OS Independent
Requires-Dist: pycorenlp
Requires-Dist: numpy
